[
    {
      "year": 1930,
      "host": "Uruguay",
      "winner": "Uruguay",
      "second": "Argentina",
      "third": "USA",
      "fourth": "Yugoslavia",
      "goals_scored": 70,
      "teams": 13,
      "games": 18,
      "attendance": 434000
    },
    {
      "year": 1934,
      "host": "Italy",
      "winner": "Italy",
      "second": "Czechoslovakia",
      "third": "Germany",
      "fourth": "Austria",
      "goals_scored": 70,
      "teams": 16,
      "games": 17,
      "attendance": 395000
    },
    {
      "year": 1938,
      "host": "France",
      "winner": "Italy",
      "second": "Hungary",
      "third": "Brazil",
      "fourth": "Sweden",
      "goals_scored": 84,
      "teams": 15,
      "games": 18,
      "attendance": 483000
    },
    {
      "year": 1950,
      "host": "Brazil",
      "winner": "Uruguay",
      "second": "Brazil",
      "third": "Sweden",
      "fourth": "Spain",
      "goals_scored": 88,
      "teams": 13,
      "games": 22,
      "attendance": 1337000
    },
    {
      "year": 1954,
      "host": "Switzerland",
      "winner": "West Germany",
      "second": "Hungary",
      "third": "Austria",
      "fourth": "Uruguay",
      "goals_scored": 140,
      "teams": 16,
      "games": 26,
      "attendance": 943000
    },
    {
      "year": 1958,
      "host": "Sweden",
      "winner": "Brazil",
      "second": "Sweden",
      "third": "France",
      "fourth": "West Germany",
      "goals_scored": 126,
      "teams": 16,
      "games": 35,
      "attendance": 868000
    },
    {
      "year": 1962,
      "host": "Chile",
      "winner": "Brazil",
      "second": "Czechoslovakia",
      "third": "Chile",
      "fourth": "Yugoslavia",
      "goals_scored": 89,
      "teams": 16,
      "games": 32,
      "attendance": 776000
    },
    {
      "year": 1966,
      "host": "England",
      "winner": "England",
      "second": "West Germany",
      "third": "Portugal",
      "fourth": "Soviet Union",
      "goals_scored": 89,
      "teams": 16,
      "games": 32,
      "attendance": 1614677
    },
    {
      "year": 1970,
      "host": "Mexico",
      "winner": "Brazil",
      "second": "Italy",
      "third": "West Germany",
      "fourth": "Uruguay",
      "goals_scored": 95,
      "teams": 16,
      "games": 32,
      "attendance": 1673975
    },
    {
      "year": 1974,
      "host": "Germany",
      "winner": "West Germany",
      "second": "Netherlands",
      "third": "Poland",
      "fourth": "Brazil",
      "goals_scored": 97,
      "teams": 16,
      "games": 38,
      "attendance": 1774022
    },
    {
      "year": 1978,
      "host": "Argentina",
      "winner": "Argentina",
      "second": "Netherlands",
      "third": "Brazil",
      "fourth": "Italy",
      "goals_scored": 102,
      "teams": 16,
      "games": 38,
      "attendance": 1610215
    },
    {
      "year": 1982,
      "host": "Spain",
      "winner": "Italy",
      "second": "West Germany",
      "third": "Poland",
      "fourth": "France",
      "goals_scored": 146,
      "teams": 24,
      "games": 52,
      "attendance": 1856277
    },
    {
      "year": 1986,
      "host": "Mexico",
      "winner": "Argentina",
      "second": "West Germany",
      "third": "France",
      "fourth": "Belgium",
      "goals_scored": 132,
      "teams": 24,
      "games": 52,
      "attendance": 2407431
    },
    {
      "year": 1990,
      "host": "Italy",
      "winner": "West Germany",
      "second": "Argentina",
      "third": "Italy",
      "fourth": "England",
      "goals_scored": 115,
      "teams": 24,
      "games": 52,
      "attendance": 2527348
    },
    {
      "year": 1994,
      "host": "USA",
      "winner": "Brazil",
      "second": "Italy",
      "third": "Sweden",
      "fourth": "Bulgaria",
      "goals_scored": 141,
      "teams": 24,
      "games": 52,
      "attendance": 3568567
    },
    {
      "year": 1998,
      "host": "France",
      "winner": "France",
      "second": "Brazil",
      "third": "Croatia",
      "fourth": "Netherlands",
      "goals_scored": 171,
      "teams": 32,
      "games": 64,
      "attendance": 2859234
    },
    {
      "year": 2002,
      "host": "Japan, South Korea",
      "winner": "Brazil",
      "second": "Germany",
      "third": "Turkey",
      "fourth": "South Korea",
      "goals_scored": 161,
      "teams": 32,
      "games": 64,
      "attendance": 2724604
    },
    {
      "year": 2006,
      "host": "Germany",
      "winner": "Italy",
      "second": "France",
      "third": "Germany",
      "fourth": "Portugal",
      "goals_scored": 147,
      "teams": 32,
      "games": 64,
      "attendance": 3367000
    },
    {
      "year": 2010,
      "host": "South Africa",
      "winner": "Spain",
      "second": "Netherlands",
      "third": "Germany",
      "fourth": "Uruguay",
      "goals_scored": 145,
      "teams": 32,
      "games": 64,
      "attendance": 2167984
    },
    {
      "year": 2014,
      "host": "Brazil",
      "winner": "Germany",
      "second": "Argentina",
      "third": "Netherlands",
      "fourth": "Brazil",
      "goals_scored": 171,
      "teams": 32,
      "games": 64,
      "attendance": 3441450
    },
    {
      "year": 2018,
      "host": "Russia",
      "winner": "France",
      "second": "Croatia",
      "third": "Belgium",
      "fourth": "England",
      "goals_scored": 169,
      "teams": 32,
      "games": 64,
      "attendance": 3031768
    }
  ]